nti.recipes.passwords-1.0.0-py2.7-nspkg.pth
nti/recipes/passwords/__init__.py
nti/recipes/passwords/tests/__init__.py
nti/recipes/passwords/tests/test_passwords.py
nti.recipes.passwords-1.0.0.dist-info/DESCRIPTION.rst
nti.recipes.passwords-1.0.0.dist-info/METADATA
nti.recipes.passwords-1.0.0.dist-info/RECORD
nti.recipes.passwords-1.0.0.dist-info/WHEEL
nti.recipes.passwords-1.0.0.dist-info/entry_points.txt
nti.recipes.passwords-1.0.0.dist-info/metadata.json
nti.recipes.passwords-1.0.0.dist-info/namespace_packages.txt
nti.recipes.passwords-1.0.0.dist-info/top_level.txt
nti.recipes.passwords-1.0.0.dist-info/zip-safe
