Metadata-Version: 2.0
Name: nti.recipes.passwords
Version: 1.0.0
Summary: zc.buildout recipes for securely storing passwords in version control
Home-page: https://github.com/NextThought/nti.recipes.passwords
Author: Jason Madden
Author-email: open-source@nextthought.com
License: Apache
Keywords: buildout password
Platform: UNKNOWN
Classifier: Development Status :: 5 - Production/Stable
Classifier: Intended Audience :: Developers
Classifier: Natural Language :: English
Classifier: Operating System :: OS Independent
Classifier: Programming Language :: Python :: 2
Classifier: Programming Language :: Python :: 2.7
Classifier: Programming Language :: Python :: 3
Classifier: Programming Language :: Python :: 3.6
Classifier: Programming Language :: Python :: Implementation :: CPython
Classifier: Programming Language :: Python :: Implementation :: PyPy
Classifier: Framework :: Buildout
Requires-Dist: setuptools
Requires-Dist: zc.buildout
Requires-Dist: zc.recipe.deployment
Requires-Dist: cryptography
Provides-Extra: test
Requires-Dist: pyhamcrest; extra == 'test'
Requires-Dist: zope.testrunner; extra == 'test'
Requires-Dist: fudge; extra == 'test'
